syntemp/__init__.py
syntemp/__main__.py
syntemp/auto_template.py
syntemp/lib_isomorphism.py
syntemp/pipeline.py
syntemp/run_compose.py
syntemp/SynAAM/RDT_2.4.1.jar
syntemp/SynAAM/__init__.py
syntemp/SynAAM/aam_postprocess.py
syntemp/SynAAM/aam_validator.py
syntemp/SynAAM/atom_map_consensus.py
syntemp/SynAAM/graphormer_wrapper.py
syntemp/SynAAM/local_mapper_wrapper.py
syntemp/SynAAM/rdt_wrapper.py
syntemp/SynAAM/rxn_mapper_wrapper.py
syntemp/SynChemistry/__init__.py
syntemp/SynChemistry/balance_checker.py
syntemp/SynChemistry/deionize.py
syntemp/SynChemistry/graph_to_mol.py
syntemp/SynChemistry/mol_to_graph.py
syntemp/SynChemistry/neutralize.py
syntemp/SynChemistry/tautomerize.py
syntemp/SynComp/__init__.py
syntemp/SynComp/rule_compose.py
syntemp/SynComp/valence_constrain.py
syntemp/SynITS/__init__.py
syntemp/SynITS/hydrogen_utils.py
syntemp/SynITS/its_arbitrary.py
syntemp/SynITS/its_construction.py
syntemp/SynITS/its_extraction.py
syntemp/SynITS/its_hadjuster.py
syntemp/SynRule/__init__.py
syntemp/SynRule/auto_cat.py
syntemp/SynRule/hierarchical_clustering.py
syntemp/SynRule/longest_path.py
syntemp/SynRule/prune_template.py
syntemp/SynRule/rc_cluster.py
syntemp/SynRule/reduce_reactions.py
syntemp/SynRule/rule_cluster.py
syntemp/SynRule/rule_decompose.py
syntemp/SynRule/rule_engine.py
syntemp/SynRule/rule_writing.py
syntemp/SynRule/rules_extraction.py
syntemp/SynVis/__init__.py
syntemp/SynVis/chemical_graph_visualizer.py
syntemp/SynVis/chemical_reaction_visualizer.py
syntemp/SynVis/its_visualizer.py
syntemp/SynVis/rule_vis.py
syntemp/utils/__init__.py
syntemp/utils/_misc.py
syntemp/utils/chemutils.py
syntemp/utils/graph_utils.py
syntemp-1.0.2.dist-info/METADATA
syntemp-1.0.2.dist-info/WHEEL
syntemp-1.0.2.dist-info/licenses/LICENSE
syntemp-1.0.2.dist-info/RECORD
