Metadata-Version: 2.4
Name: syntemp
Version: 1.0.2
Summary: Graph-based reaction templates extraction
Project-URL: homepage, https://github.com/TieuLongPhan/SynTemp
Project-URL: source, https://github.com/TieuLongPhan/SynTemp
Project-URL: issues, https://github.com/TieuLongPhan/SynTemp/issues
Author-email: Tieu Long Phan <tieu@bioinf.uni-leipzig.de>
License-File: LICENSE
Classifier: License :: OSI Approved :: MIT License
Classifier: Operating System :: OS Independent
Classifier: Programming Language :: Python :: 3
Classifier: Programming Language :: Python :: 3.11
Requires-Python: >=3.11
Requires-Dist: synkit>=0.0.9
Requires-Dist: synrbl>=1.0.1
Provides-Extra: all
Requires-Dist: chython==1.78; extra == 'all'
Requires-Dist: chytorch-rxnmap>=1.4; extra == 'all'
Requires-Dist: chytorch>=1.65; extra == 'all'
Requires-Dist: dgl==2.1.0; extra == 'all'
Requires-Dist: dgllife==0.3.2; extra == 'all'
Requires-Dist: localmapper>=0.1.5; extra == 'all'
Requires-Dist: rxn-chem-utils>=1.6.0; extra == 'all'
Requires-Dist: rxn-utils>=2.0.0; extra == 'all'
Requires-Dist: rxnmapper>=0.4.1; extra == 'all'
Requires-Dist: torch==2.2.0; extra == 'all'
Requires-Dist: torchdata==0.7.1; extra == 'all'
Requires-Dist: transformers==4.51.1; extra == 'all'
